{
  "title": "SajuOS_Logic_STRU_M_098",
  "rulecards": [
    {
      "id": "RC-f5ddbee229",
      "topic": "STRUCTURE",
      "priority": 9,
      "trigger": {
        "month": "묘",
        "day": "경자",
        "fire": true
      },
      "mechanism": "병화가 목생화를 원활히 하여 수색목의 왜곡을 방지함.",
      "interpretation": "병화가 있으면 잠오형 구조가 긍정적으로 작용하며, 화가 없으면 수색목이 왜곡될 가능성이 있음.",
      "action": "사주에 병화가 있는지 확인하고, 없으면 화의 역할을 보완할 방법을 모색.",
      "cautions": [
        "화가 없을 경우 수색목이 왜곡될 수 있음.",
        "잠오형을 지나치게 부정적으로 해석하지 말 것."
      ],
      "tags": [
        "병화",
        "수색목",
        "잠오형",
        "묘월",
        "경자일주"
      ]
    },
    {
      "id": "RC-9fd95d4398",
      "topic": "WEALTH",
      "priority": 8,
      "trigger": {
        "month": "묘",
        "day": "경금",
        "earth": true
      },
      "mechanism": "토가 재를 안정화시켜 자산의 가치를 고정함.",
      "interpretation": "토가 있어야 재의 안정성이 확보되고, 자산 축적이 가능.",
      "action": "토 운에서 자산 매입이나 재테크를 계획.",
      "cautions": [
        "토가 없으면 재의 유동성이 커져 자산 축적이 어려움.",
        "현금 흐름만으로 안정성을 기대하지 말 것."
      ],
      "tags": [
        "토",
        "재",
        "자산",
        "묘월",
        "경금"
      ]
    },
    {
      "id": "RC-384f913c17",
      "topic": "CAREER",
      "priority": 7,
      "trigger": {
        "month": "묘",
        "day": "경금",
        "fire": "정화"
      },
      "mechanism": "정화는 경금을 구체적이고 안정적으로 다룰 수 있게 함.",
      "interpretation": "정화가 있으면 직업 안정성이 높아지고, 특정 직무에 적합.",
      "action": "정화가 있는 경우 안정적인 직업군을 선택.",
      "cautions": [
        "정화가 없으면 직업 유동성이 커질 수 있음.",
        "병화와 정화의 역할 차이를 이해할 것."
      ],
      "tags": [
        "정화",
        "경금",
        "직업 안정성",
        "묘월",
        "직무"
      ]
    },
    {
      "id": "RC-eca0533b38",
      "topic": "CAREER",
      "priority": 6,
      "trigger": {
        "month": "묘",
        "day": "경금",
        "fire": "병화"
      },
      "mechanism": "병화는 경금의 직업 유동성을 증가시킴.",
      "interpretation": "병화가 있으면 다양한 직무를 경험할 가능성이 높음.",
      "action": "병화가 있는 경우 직업 선택의 폭을 넓히고, 유연성을 유지.",
      "cautions": [
        "직업 안정성이 떨어질 수 있음.",
        "다양한 경험이 장점이지만, 집중력 부족에 유의."
      ],
      "tags": [
        "병화",
        "경금",
        "직업 유동성",
        "묘월",
        "다양성"
      ]
    },
    {
      "id": "RC-d40bc0dc31",
      "topic": "WEALTH",
      "priority": 7,
      "trigger": {
        "month": "묘",
        "day": "경금",
        "fire": true,
        "earth": true
      },
      "mechanism": "화와 토가 재를 다루는 데 중요한 역할을 함.",
      "interpretation": "화와 토가 함께 있으면 재를 효과적으로 관리하고 축적 가능.",
      "action": "화와 토의 조화를 확인하고, 재테크 전략을 세움.",
      "cautions": [
        "화와 토가 없으면 재 관리가 어려울 수 있음.",
        "재의 유동성을 과소평가하지 말 것."
      ],
      "tags": [
        "화",
        "토",
        "재",
        "재테크",
        "묘월"
      ]
    },
    {
      "id": "RC-7aad3f326f",
      "topic": "RELATION",
      "priority": 5,
      "trigger": {
        "month": "묘",
        "day": "경자",
        "fire": true
      },
      "mechanism": "병화가 수색목의 왜곡을 방지하고, 관계의 조화를 유지.",
      "interpretation": "병화가 있으면 관계에서 긍정적인 상호작용이 가능.",
      "action": "병화의 유무를 확인하고, 관계 개선에 활용.",
      "cautions": [
        "병화가 없으면 관계에서 갈등이 생길 수 있음.",
        "수색목의 왜곡을 방지하려면 화의 역할을 보완."
      ],
      "tags": [
        "병화",
        "수색목",
        "관계",
        "묘월",
        "경자일주"
      ]
    },
    {
      "id": "RC-9fbb49372c",
      "topic": "GENERAL",
      "priority": 6,
      "trigger": {
        "note": "묘월의 디테일과 구체성에 대한 설명"
      },
      "mechanism": "묘월은 구체적이고 세부적인 성향을 강조.",
      "interpretation": "묘월은 꼼꼼하고 디테일을 중시하는 성향을 나타냄.",
      "action": "묘월의 성향을 활용해 세부적인 작업에 집중.",
      "cautions": [
        "추상적인 접근보다는 구체적인 계획이 필요.",
        "디테일에 집착하여 큰 그림을 놓치지 않도록 주의."
      ],
      "tags": [
        "묘월",
        "디테일",
        "구체성",
        "성향",
        "계획"
      ]
    },
    {
      "id": "RC-6aa6c9d4fc",
      "topic": "CAREER",
      "priority": 8,
      "trigger": {
        "month": "묘",
        "day": "경호",
        "fire": "정화"
      },
      "mechanism": "정화는 경호일주의 직업 안정성을 높임.",
      "interpretation": "정화가 있으면 맞춤형 직업군에 적합.",
      "action": "정화가 있는 경우 안정적인 직업을 선택.",
      "cautions": [
        "정화가 없으면 직업의 유동성이 커질 수 있음.",
        "정화와 병화의 차이를 이해하고 활용."
      ],
      "tags": [
        "정화",
        "경호일주",
        "직업 안정성",
        "묘월",
        "맞춤형"
      ]
    },
    {
      "topic": "TEN_GODS",
      "priority": 9,
      "trigger": {
        "type": "정재",
        "behavior": "정보를 숨김"
      },
      "mechanism": "정재는 개인적 이익을 중시하며 정보를 독점하려는 경향이 있음.",
      "interpretation": "정재는 자신의 이익을 위해 정보를 공유하지 않으려는 성향을 보임.",
      "action": "정재가 강한 사람과 협력 시 정보 공유를 유도할 방법을 고민해야 함.",
      "cautions": [
        "정재의 독점적 성향이 협력에 장애가 될 수 있음."
      ],
      "tags": [
        "정재",
        "정보",
        "독점",
        "개인주의",
        "협력"
      ],
      "id": "RC-b42f359432"
    },
    {
      "topic": "TEN_GODS",
      "priority": 8,
      "trigger": {
        "type": "편재",
        "behavior": "정보를 홍보"
      },
      "mechanism": "편재는 대중적이고 개방적인 성향으로 정보를 널리 알리려 함.",
      "interpretation": "편재는 정보를 공유하며 대중과의 연결을 중시함.",
      "action": "편재가 강한 사람은 정보의 신뢰성을 검증하며 활용해야 함.",
      "cautions": [
        "과도한 홍보로 정보의 신뢰도가 낮아질 수 있음."
      ],
      "tags": [
        "편재",
        "정보",
        "홍보",
        "대중성",
        "신뢰성"
      ],
      "id": "RC-fd4cda5eba"
    },
    {
      "topic": "RELATION",
      "priority": 7,
      "trigger": {
        "type": "원진",
        "present": true
      },
      "mechanism": "원진은 감정적 갈등을 유발할 수 있는 관계적 요소임.",
      "interpretation": "원진이 있다고 반드시 갈등이 발생하는 것은 아님.",
      "action": "원진 관계를 가진 사람과는 감정적 대응을 피하고 객관적으로 접근해야 함.",
      "cautions": [
        "원진을 과도하게 부정적으로 해석하지 말 것."
      ],
      "tags": [
        "원진",
        "갈등",
        "관계",
        "감정",
        "객관성"
      ],
      "id": "RC-f232ae9bb7"
    },
    {
      "topic": "LOVE",
      "priority": 8,
      "trigger": {
        "type": "암합",
        "context": "애정문제"
      },
      "mechanism": "암합은 보이지 않는 곳에서의 관계 형성을 의미함.",
      "interpretation": "암합은 애정 문제에서 비밀스러운 관계를 나타낼 수 있음.",
      "action": "암합이 있는 경우 관계의 투명성을 유지하려고 노력해야 함.",
      "cautions": [
        "암합이 부정적 상황으로 이어질 가능성에 주의."
      ],
      "tags": [
        "암합",
        "애정",
        "비밀",
        "관계",
        "투명성"
      ],
      "id": "RC-001a4ceda4"
    },
    {
      "topic": "CAREER",
      "priority": 9,
      "trigger": {
        "type": "비겁",
        "behavior": "고집이 강함"
      },
      "mechanism": "비겁은 감정적이고 고집스러운 성향을 나타냄.",
      "interpretation": "비겁이 강한 사람은 설득이 어려우며 자신의 감정에 따라 행동함.",
      "action": "비겁이 강한 사람과 협력 시 감정적 접근을 피하고 논리적 근거를 제시해야 함.",
      "cautions": [
        "비겁의 고집이 협력과 조화를 방해할 수 있음."
      ],
      "tags": [
        "비겁",
        "고집",
        "감정",
        "설득",
        "협력"
      ],
      "id": "RC-3dd4fcccc5"
    },
    {
      "topic": "WEALTH",
      "priority": 8,
      "trigger": {
        "type": "재성",
        "behavior": "전투력 강함"
      },
      "mechanism": "재성을 다루는 능력이 강하면 재물을 철저히 통제하려는 성향이 나타남.",
      "interpretation": "재성의 전투력이 강한 사람은 재물 관리에 있어 강한 책임감을 보임.",
      "action": "재성의 전투력을 긍정적으로 활용하여 재정적 안정성을 확보해야 함.",
      "cautions": [
        "과도한 통제가 관계에 부정적 영향을 미칠 수 있음."
      ],
      "tags": [
        "재성",
        "전투력",
        "통제",
        "책임감",
        "재정"
      ],
      "id": "RC-d16078924e"
    },
    {
      "topic": "STRUCTURE",
      "priority": 7,
      "trigger": {
        "type": "암합",
        "context": "외교적 능력"
      },
      "mechanism": "암합은 겉으로는 갈등을 보이지만 뒤로는 화해를 이루는 구조를 나타냄.",
      "interpretation": "암합이 있는 사람은 외교적이고 협상 능력이 뛰어남.",
      "action": "암합을 활용하여 갈등 상황에서 중재 역할을 수행할 수 있음.",
      "cautions": [
        "암합이 부정적 상황으로 오해받지 않도록 주의."
      ],
      "tags": [
        "암합",
        "외교",
        "협상",
        "갈등",
        "중재"
      ],
      "id": "RC-dabdcbc193"
    },
    {
      "topic": "CAREER",
      "priority": 8,
      "trigger": {
        "type": "식상격",
        "behavior": "재성 활용"
      },
      "mechanism": "식상격은 재성을 활용하여 공간을 채우고 활용하는 능력을 나타냄.",
      "interpretation": "식상격은 창업이나 자영업에 적합한 구조를 보임.",
      "action": "식상격의 재성을 활용하여 창업 아이템을 구체화하고 실행해야 함.",
      "cautions": [
        "재성 활용이 과도하면 자원 낭비로 이어질 수 있음."
      ],
      "tags": [
        "식상격",
        "재성",
        "창업",
        "자영업",
        "공간활용"
      ],
      "id": "RC-80f8c8dace"
    },
    {
      "topic": "TIMING",
      "priority": 9,
      "trigger": {
        "type": "재극인",
        "context": "화운"
      },
      "mechanism": "재극인은 화운에서 재물의 가치 상승을 유도함.",
      "interpretation": "화운에서 재산을 매도하면 높은 가치를 얻을 가능성이 큼.",
      "action": "화운이 올 때 재산 매도를 계획해야 함.",
      "cautions": [
        "화운이 아닌 시기에 매도하면 손실 가능성이 있음."
      ],
      "tags": [
        "재극인",
        "화운",
        "재산",
        "매도",
        "가치상승"
      ],
      "id": "RC-1d3257225b"
    },
    {
      "topic": "GENERAL",
      "priority": 7,
      "trigger": {
        "note": "경진일조의 묘월"
      },
      "mechanism": "경진일조의 묘월은 현실적이고 구체적인 사고를 유도함.",
      "interpretation": "경진일조의 묘월은 상상력보다는 실질적이고 현실적인 접근을 중시함.",
      "action": "경진일조의 묘월을 가진 사람은 현실적인 목표를 설정하고 실행해야 함.",
      "cautions": [
        "과도한 현실주의가 창의성을 억제할 수 있음."
      ],
      "tags": [
        "경진일조",
        "묘월",
        "현실주의",
        "구체성",
        "목표설정"
      ],
      "id": "RC-5e3f72e043"
    }
  ],
  "notes": [
    "텍스트가 매우 길고 복잡하여 일부 규칙은 요약 및 단순화됨.",
    "추가적인 세부 규칙은 다음 청크에서 다룰 수 있음."
  ],
  "schema_version": "rulecards.v1",
  "module_code": "SajuOS_STRU_098",
  "updated_at": "2025-12-23T20:27:24"
}