{
  "title": "SajuOS_Logic_TEN_022",
  "rulecards": [
    {
      "id": "RC-3326247010",
      "topic": "TEN_GODS",
      "priority": 9,
      "trigger": {
        "ten_god": "정재",
        "day_master": "이모일주"
      },
      "mechanism": "정재가 강하고 밀착도가 높아 내 것처럼 행동하는 성향이 강함.",
      "interpretation": "이모일주는 주변 사람들에게 친절하고 자상하며, 내 것처럼 행동하는 성향이 강하다.",
      "action": "이모일주와 함께 일하거나 관계를 맺을 때 그들의 헌신적인 태도를 이해하고 존중하라.",
      "cautions": [
        "이모일주의 행동이 오해를 불러일으킬 수 있음.",
        "모든 사람에게 동일하게 대하는 태도가 착각을 유발할 수 있음."
      ],
      "tags": [
        "정재",
        "이모일주",
        "밀착도",
        "친절",
        "오해"
      ]
    },
    {
      "id": "RC-fac3a5d564",
      "topic": "TEN_GODS",
      "priority": 8,
      "trigger": {
        "ten_god": "정재",
        "day_master": "괴사일주"
      },
      "mechanism": "괴사일주는 정재의 성향이 있지만 밀착도가 이모일주보다 낮음.",
      "interpretation": "괴사일주는 친절하지만 이모일주처럼 강한 밀착도는 보이지 않음.",
      "action": "괴사일주의 친절함을 이해하되, 그들의 행동을 과대해석하지 않도록 주의하라.",
      "cautions": [
        "괴사일주의 친절함이 오해를 불러일으킬 수 있음."
      ],
      "tags": [
        "정재",
        "괴사일주",
        "친절",
        "밀착도",
        "오해"
      ]
    },
    {
      "id": "RC-0a6c7c2273",
      "topic": "ELEMENTS",
      "priority": 7,
      "trigger": {
        "elements": [
          "수",
          "화"
        ],
        "balance": "조우 해결"
      },
      "mechanism": "수화 조우가 해결된 경우, 정재의 성향이 더욱 부드럽고 매력적으로 나타남.",
      "interpretation": "수화 조우가 해결된 사람은 귀엽고 매력적인 성향을 보이며, 주변에서 호감을 얻기 쉬움.",
      "action": "수화 조우가 해결된 사람의 매력을 활용하여 대인관계를 원활히 하라.",
      "cautions": [
        "매력적인 성향이 오해를 불러일으킬 수 있음."
      ],
      "tags": [
        "수",
        "화",
        "조우",
        "매력",
        "호감"
      ]
    },
    {
      "id": "RC-40ea3606a2",
      "topic": "TEN_GODS",
      "priority": 6,
      "trigger": {
        "ten_god": "정재",
        "day_master": "이모일주",
        "gender": "여성"
      },
      "mechanism": "여성 이모일주는 남성들에게 특별히 착각을 유발할 가능성이 높음.",
      "interpretation": "여성 이모일주는 남성들에게 특별히 매력적으로 보이며, 오해를 살 수 있음.",
      "action": "여성 이모일주는 자신의 행동이 오해를 불러일으킬 수 있음을 인지하고 조심하라.",
      "cautions": [
        "남성들이 특별히 착각할 가능성이 높음."
      ],
      "tags": [
        "정재",
        "이모일주",
        "여성",
        "매력",
        "오해"
      ]
    },
    {
      "id": "RC-b6ca658560",
      "topic": "TEN_GODS",
      "priority": 6,
      "trigger": {
        "ten_god": "정재",
        "day_master": "이모일주",
        "gender": "남성"
      },
      "mechanism": "남성 이모일주는 주변 사람들에게 친절하고 자상한 태도로 인기를 얻음.",
      "interpretation": "남성 이모일주는 주변 사람들에게 호감을 얻으며, 특히 여성들에게 인기가 많음.",
      "action": "남성 이모일주는 자신의 행동이 오해를 불러일으킬 수 있음을 인지하고 적절히 조율하라.",
      "cautions": [
        "여성들이 착각할 가능성이 있음."
      ],
      "tags": [
        "정재",
        "이모일주",
        "남성",
        "친절",
        "인기"
      ]
    },
    {
      "id": "RC-2020a8525a",
      "topic": "TEN_GODS",
      "priority": 5,
      "trigger": {
        "ten_god": "정재",
        "day_master": "이모일주",
        "workplace": true
      },
      "mechanism": "이모일주는 직장에서 내 것처럼 행동하며 헌신적인 태도를 보임.",
      "interpretation": "이모일주는 직장에서 신뢰받는 직원이 될 가능성이 높음.",
      "action": "이모일주의 헌신적인 태도를 인정하고, 적절한 피드백을 제공하라.",
      "cautions": [
        "과도한 헌신이 오히려 갈등을 유발할 수 있음."
      ],
      "tags": [
        "정재",
        "이모일주",
        "직장",
        "헌신",
        "피드백"
      ]
    },
    {
      "id": "RC-7e13921178",
      "topic": "ELEMENTS",
      "priority": 5,
      "trigger": {
        "elements": [
          "4화",
          "5화"
        ]
      },
      "mechanism": "4화는 에너지가 사방으로 퍼지고, 5화는 특정 방향으로 집중됨.",
      "interpretation": "4화는 밀착도가 낮고, 5화는 밀착도가 높음.",
      "action": "4화와 5화의 차이를 이해하고, 상황에 맞게 활용하라.",
      "cautions": [
        "4화는 집중력이 낮아 보일 수 있음."
      ],
      "tags": [
        "4화",
        "5화",
        "밀착도",
        "집중력",
        "에너지"
      ]
    }
  ],
  "notes": [
    "이모일주와 괴사일주의 차이점에 대한 설명이 포함됨.",
    "수화 조우가 해결된 경우의 특성이 언급됨."
  ],
  "schema_version": "rulecards.v1",
  "module_code": "SajuOS_TEN_022",
  "updated_at": "2025-12-23T20:27:26"
}