{
  "title": "SajuOS_Logic_ELEM_011",
  "rulecards": [
    {
      "id": "RC-bd13d81cb8",
      "topic": "ELEMENTS",
      "priority": 9,
      "trigger": {
        "element": "신금",
        "interaction": "화극금"
      },
      "mechanism": "신금은 화를 분리하고 쓸모 있는 것을 남기는 역할을 한다.",
      "interpretation": "신금이 있는 사람은 실속 있는 선택과 분별력이 뛰어나다.",
      "action": "인간관계나 정보 처리에서 신중히 선택하고 불필요한 것을 제거하라.",
      "cautions": [
        "화가 없으면 신금의 역할이 제한될 수 있다."
      ],
      "tags": [
        "신금",
        "화극금",
        "분별력",
        "실속",
        "정보처리"
      ]
    },
    {
      "id": "RC-282461e8c5",
      "topic": "ELEMENTS",
      "priority": 8,
      "trigger": {
        "element": "유금",
        "interaction": "화극금"
      },
      "mechanism": "유금은 화를 분리하는 능력이 약하며, 유지하려는 성향이 강하다.",
      "interpretation": "유금은 보존과 안정성을 중시하지만, 변화에 약할 수 있다.",
      "action": "유금의 보존적 성향을 활용하되, 변화에 유연성을 가지도록 노력하라.",
      "cautions": [
        "화가 강하면 유금이 손상될 수 있다."
      ],
      "tags": [
        "유금",
        "화극금",
        "보존",
        "안정성",
        "변화"
      ]
    },
    {
      "id": "RC-2cc8a22c5b",
      "topic": "RELATION",
      "priority": 7,
      "trigger": {
        "relation": "인유원진"
      },
      "mechanism": "인유원진은 극의 관계가 무자비하게 작용하여 갈등이 반복된다.",
      "interpretation": "인유원진은 해결되지 않는 갈등과 상처를 의미한다.",
      "action": "원진 관계를 인식하고, 갈등을 완화할 방법을 모색하라.",
      "cautions": [
        "원진은 해결이 어렵고 장기적인 갈등을 초래할 수 있다."
      ],
      "tags": [
        "인유원진",
        "갈등",
        "반복",
        "관계",
        "해결"
      ]
    },
    {
      "id": "RC-ef5c890aa9",
      "topic": "RELATION",
      "priority": 8,
      "trigger": {
        "relation": "인신충"
      },
      "mechanism": "인신충은 방위와 음양이 반대되어 충의 조건을 충족한다.",
      "interpretation": "인신충은 강한 변화와 갈등을 의미하며, 문제를 해결할 기회를 제공한다.",
      "action": "충의 에너지를 활용해 변화를 수용하고 새로운 방향을 모색하라.",
      "cautions": [
        "충은 긍정적일 수 있지만, 지나친 갈등은 피해야 한다."
      ],
      "tags": [
        "인신충",
        "변화",
        "갈등",
        "방향",
        "해결"
      ]
    },
    {
      "id": "RC-7e553d3918",
      "topic": "ELEMENTS",
      "priority": 7,
      "trigger": {
        "element": "수",
        "state": "강함"
      },
      "mechanism": "수는 에너지를 응집하고 유지하는 힘을 상징한다.",
      "interpretation": "수가 강한 사람은 집중력과 인내력이 뛰어나다.",
      "action": "집중력을 활용해 장기적인 목표를 설정하고 성취하라.",
      "cautions": [
        "수가 지나치게 강하면 고립되거나 감정 표현이 어려울 수 있다."
      ],
      "tags": [
        "수",
        "응집",
        "집중력",
        "인내",
        "유지"
      ]
    },
    {
      "id": "RC-f0df4510eb",
      "topic": "ELEMENTS",
      "priority": 6,
      "trigger": {
        "element": "수",
        "state": "약함"
      },
      "mechanism": "약한 수는 에너지가 흩어져 집중력이 부족할 수 있다.",
      "interpretation": "수가 약하면 지속적인 노력이 어렵고 산만할 수 있다.",
      "action": "집중력을 키우기 위해 환경을 정리하고 명확한 목표를 설정하라.",
      "cautions": [
        "수가 약하면 쉽게 지치거나 산만해질 수 있다."
      ],
      "tags": [
        "수",
        "약함",
        "집중력 부족",
        "목표",
        "산만"
      ]
    },
    {
      "id": "RC-b4dea089f6",
      "topic": "RELATION",
      "priority": 7,
      "trigger": {
        "relation": "묘유충"
      },
      "mechanism": "묘유충은 방위와 음양이 반대되어 충의 조건을 충족한다.",
      "interpretation": "묘유충은 강한 변화와 갈등을 의미하며, 문제를 해결할 기회를 제공한다.",
      "action": "충의 에너지를 활용해 변화를 수용하고 새로운 방향을 모색하라.",
      "cautions": [
        "충은 긍정적일 수 있지만, 지나친 갈등은 피해야 한다."
      ],
      "tags": [
        "묘유충",
        "변화",
        "갈등",
        "방향",
        "해결"
      ]
    },
    {
      "id": "RC-947a110783",
      "topic": "ELEMENTS",
      "priority": 6,
      "trigger": {
        "element": "수",
        "interaction": "화"
      },
      "mechanism": "수와 화는 서로 반대되는 에너지로 균형을 이룬다.",
      "interpretation": "수와 화의 균형은 삶의 안정성과 활력을 제공한다.",
      "action": "수와 화의 균형을 유지하기 위해 적절한 휴식과 활동을 병행하라.",
      "cautions": [
        "수와 화의 불균형은 삶의 불안정성을 초래할 수 있다."
      ],
      "tags": [
        "수",
        "화",
        "균형",
        "안정성",
        "활력"
      ]
    },
    {
      "id": "RC-dc0891fb48",
      "topic": "ELEMENTS",
      "priority": 5,
      "trigger": {
        "element": "수",
        "state": "응집력"
      },
      "mechanism": "수는 에너지를 모으고 응집하는 역할을 한다.",
      "interpretation": "응집력이 강한 수는 안정성과 지속성을 의미한다.",
      "action": "응집력을 활용해 장기적인 계획을 세우고 실행하라.",
      "cautions": [
        "응집력이 지나치면 고립되거나 변화에 둔감해질 수 있다."
      ],
      "tags": [
        "수",
        "응집력",
        "안정성",
        "지속성",
        "계획"
      ]
    },
    {
      "id": "RC-17c6eb4bc8",
      "topic": "RELATION",
      "priority": 6,
      "trigger": {
        "relation": "인유원진",
        "year": "갑진"
      },
      "mechanism": "갑진년의 진토는 인유원진을 완화하는 스팟 에너지로 작용한다.",
      "interpretation": "갑진년은 인유원진의 갈등을 완화하고 해결의 기회를 제공한다.",
      "action": "갑진년의 기회를 활용해 갈등을 해결하고 관계를 개선하라.",
      "cautions": [
        "스팟 에너지는 일시적이므로 지속적인 노력이 필요하다."
      ],
      "tags": [
        "인유원진",
        "갑진년",
        "스팟 에너지",
        "갈등 완화",
        "관계 개선"
      ]
    },
    {
      "id": "RC-569b888f28",
      "topic": "ELEMENTS",
      "priority": 9,
      "trigger": {
        "element": "수",
        "condition": "온도 > 100도"
      },
      "mechanism": "수는 응집과 보관의 속성을 가지지만, 과도한 열로 인해 흩어질 수 있다.",
      "interpretation": "수가 흩어지면 집중력과 인내력이 약화될 수 있다.",
      "action": "수가 중요한 사주라면, 환경적 안정과 균형을 유지하도록 노력해야 한다.",
      "cautions": [
        "과도한 스트레스나 열로 인해 집중력이 저하될 수 있음"
      ],
      "tags": [
        "수",
        "응집",
        "흩어짐",
        "집중력",
        "인내력"
      ]
    },
    {
      "id": "RC-868bd96f32",
      "topic": "ELEMENTS",
      "priority": 8,
      "trigger": {
        "element": "수",
        "condition": "강한 화의 영향"
      },
      "mechanism": "화가 강하면 수의 응집력이 약화되어 흩어질 수 있다.",
      "interpretation": "수가 약화되면 감정 조절과 내면의 안정이 어려워질 수 있다.",
      "action": "화의 영향을 줄이고 수의 균형을 유지하기 위한 환경을 조성하라.",
      "cautions": [
        "화의 과잉은 수의 본질을 약화시킬 수 있음"
      ],
      "tags": [
        "수",
        "화",
        "균형",
        "응집력",
        "감정"
      ]
    },
    {
      "id": "RC-0d7c3a0c00",
      "topic": "ELEMENTS",
      "priority": 7,
      "trigger": {
        "element": "수",
        "condition": "보관의 역할"
      },
      "mechanism": "수는 보관과 감춤의 속성을 가지며, 중요한 자산과 정보를 저장한다.",
      "interpretation": "수는 재산, 문서, 비밀 등 중요한 것을 보관하는 역할을 한다.",
      "action": "중요한 자산과 정보를 안전하게 보관할 수 있는 환경을 마련하라.",
      "cautions": [
        "보관의 실패는 손실로 이어질 수 있음"
      ],
      "tags": [
        "수",
        "보관",
        "자산",
        "정보",
        "안전"
      ]
    },
    {
      "id": "RC-939a9bef8d",
      "topic": "ELEMENTS",
      "priority": 8,
      "trigger": {
        "element": "수",
        "condition": "금생수"
      },
      "mechanism": "금은 수의 응집력을 강화하고 보관 능력을 돕는다.",
      "interpretation": "금생수는 수의 본질을 강화하여 안정성과 집중력을 높인다.",
      "action": "금의 에너지를 활용하여 수의 응집력을 강화하라.",
      "cautions": [
        "금의 과잉은 수의 흐름을 방해할 수 있음"
      ],
      "tags": [
        "수",
        "금생수",
        "응집력",
        "안정성",
        "집중력"
      ]
    },
    {
      "id": "RC-e241aeb9eb",
      "topic": "ELEMENTS",
      "priority": 7,
      "trigger": {
        "element": "수",
        "condition": "청각과 연결"
      },
      "mechanism": "수는 청각과 연결되어 듣는 능력을 강화한다.",
      "interpretation": "청각이 발달한 사람은 수의 영향을 많이 받을 수 있다.",
      "action": "청각을 활용한 학습과 소통 방식을 개발하라.",
      "cautions": [
        "청각의 과민함은 스트레스를 유발할 수 있음"
      ],
      "tags": [
        "수",
        "청각",
        "듣기",
        "소통",
        "학습"
      ]
    },
    {
      "id": "RC-7a92cb3288",
      "topic": "ELEMENTS",
      "priority": 6,
      "trigger": {
        "element": "수",
        "condition": "예술적 감각"
      },
      "mechanism": "수는 감정과 연결되어 예술적 감각을 자극한다.",
      "interpretation": "수의 에너지는 음악, 문학 등 감정적 예술에 강한 영향을 미친다.",
      "action": "예술적 활동을 통해 수의 에너지를 발산하라.",
      "cautions": [
        "감정 과잉으로 인해 균형을 잃을 수 있음"
      ],
      "tags": [
        "수",
        "예술",
        "감정",
        "음악",
        "문학"
      ]
    },
    {
      "id": "RC-642956e4c3",
      "topic": "ELEMENTS",
      "priority": 9,
      "trigger": {
        "element": "임수",
        "condition": "자연 상태"
      },
      "mechanism": "임수는 자연 상태의 물로, 정화되지 않으면 사용이 어렵다.",
      "interpretation": "임수는 철학적, 정신적 가치를 추구하는 에너지를 가진다.",
      "action": "임수의 에너지를 활용하려면 정화와 구조화가 필요하다.",
      "cautions": [
        "정화되지 않은 임수는 사회적 활용이 어려움"
      ],
      "tags": [
        "임수",
        "정화",
        "철학",
        "정신",
        "자연"
      ]
    },
    {
      "id": "RC-ebc4ac8887",
      "topic": "ELEMENTS",
      "priority": 8,
      "trigger": {
        "element": "개수",
        "condition": "즉시 사용 가능"
      },
      "mechanism": "개수는 이미 정화된 물로, 즉시 사용 가능한 상태이다.",
      "interpretation": "개수는 실용적이고 즉각적인 활용이 가능한 에너지를 가진다.",
      "action": "개수의 에너지를 활용해 실용적이고 생산적인 활동을 하라.",
      "cautions": [
        "과도한 실용주의는 장기적 계획을 방해할 수 있음"
      ],
      "tags": [
        "개수",
        "실용",
        "즉시",
        "생산",
        "활용"
      ]
    },
    {
      "id": "RC-c797901c3a",
      "topic": "ELEMENTS",
      "priority": 7,
      "trigger": {
        "element": "수",
        "condition": "지식과 정보"
      },
      "mechanism": "수는 지식을 모으고 정보를 생성하는 역할을 한다.",
      "interpretation": "수는 데이터와 정보를 통해 지혜를 형성한다.",
      "action": "수의 에너지를 활용해 학습과 정보 수집에 집중하라.",
      "cautions": [
        "지식만 모으고 활용하지 않으면 비효율적일 수 있음"
      ],
      "tags": [
        "수",
        "지식",
        "정보",
        "학습",
        "지혜"
      ]
    },
    {
      "id": "RC-c2241bb0e8",
      "topic": "ELEMENTS",
      "priority": 6,
      "trigger": {
        "element": "수",
        "condition": "순환의 끝"
      },
      "mechanism": "수는 순환의 끝이자 새로운 시작을 의미한다.",
      "interpretation": "수는 죽음과 재생, 철학적 전환을 상징한다.",
      "action": "수의 에너지를 활용해 새로운 시작을 준비하라.",
      "cautions": [
        "변화에 대한 두려움은 성장을 방해할 수 있음"
      ],
      "tags": [
        "수",
        "순환",
        "죽음",
        "재생",
        "철학"
      ]
    }
  ],
  "notes": [
    "텍스트가 길고 복잡하여 일부 규칙은 요약 및 단순화되었습니다.",
    "추가적인 규칙은 다음 청크에서 계속 추출될 예정입니다."
  ],
  "schema_version": "rulecards.v1",
  "module_code": "SajuOS_ELEM_011",
  "updated_at": "2025-12-23T20:27:25"
}